admin/admin/admin.html
web3pi_proxy/__init__.py
web3pi_proxy/__main__.py
web3pi_proxy/config/__init__.py
web3pi_proxy/config/conf.py
web3pi_proxy/core/__init__.py
web3pi_proxy/core/inbound/__init__.py
web3pi_proxy/core/inbound/server.py
web3pi_proxy/core/interfaces/__init__.py
web3pi_proxy/core/interfaces/rpcnode.py
web3pi_proxy/core/interfaces/rpcrequest.py
web3pi_proxy/core/interfaces/rpcresponse.py
web3pi_proxy/core/proxy.py
web3pi_proxy/core/rpc/__init__.py
web3pi_proxy/core/rpc/cache/__init__.py
web3pi_proxy/core/rpc/cache/cacheservice.py
web3pi_proxy/core/rpc/cache/responsecacheservice.py
web3pi_proxy/core/rpc/node/__init__.py
web3pi_proxy/core/rpc/node/client_socket_pool.py
web3pi_proxy/core/rpc/node/endpoint_pool/__init__.py
web3pi_proxy/core/rpc/node/endpoint_pool/connection_pool.py
web3pi_proxy/core/rpc/node/endpoint_pool/endpoint_connection_pool.py
web3pi_proxy/core/rpc/node/endpoint_pool/load_balancers.py
web3pi_proxy/core/rpc/node/endpoint_pool/pool_manager.py
web3pi_proxy/core/rpc/node/rpcendpoint/__init__.py
web3pi_proxy/core/rpc/node/rpcendpoint/connection/__init__.py
web3pi_proxy/core/rpc/node/rpcendpoint/connection/connection_handler.py
web3pi_proxy/core/rpc/node/rpcendpoint/connection/connectiondescr.py
web3pi_proxy/core/rpc/node/rpcendpoint/connection/endpoint_connection_handler.py
web3pi_proxy/core/rpc/node/rpcendpoint/connection/endpointconnection.py
web3pi_proxy/core/rpc/node/rpcendpoint/connection/endpointconnectionstats.py
web3pi_proxy/core/rpc/node/rpcendpoint/connection/receiver.py
web3pi_proxy/core/rpc/node/rpcendpoint/connection/sender.py
web3pi_proxy/core/rpc/node/rpcendpoint/endpointimpl.py
web3pi_proxy/core/rpc/request/__init__.py
web3pi_proxy/core/rpc/request/middleware/__init__.py
web3pi_proxy/core/rpc/request/middleware/defaultmiddlewares/__init__.py
web3pi_proxy/core/rpc/request/middleware/defaultmiddlewares/authenticator.py
web3pi_proxy/core/rpc/request/middleware/defaultmiddlewares/methodvalidator.py
web3pi_proxy-0.4.dist-info/LICENSE
web3pi_proxy-0.4.dist-info/METADATA
web3pi_proxy-0.4.dist-info/WHEEL
web3pi_proxy-0.4.dist-info/entry_points.txt
web3pi_proxy-0.4.dist-info/RECORD
