Metadata-Version: 2.1
Name: web3pi-proxy
Version: 0.4
Summary: RPC Reverse Proxy - proxy to Web3 Pi Ethereum nodes
Home-page: https://github.com/Web3-Pi/web3-reverse-proxy
License: GNU GENERAL PUBLIC LICENSE Version 3
Keywords: web3pi,web3,rpi,raspberry,geth,ethereum,proxy
Requires-Python: >=3.9,<4.0
Classifier: Development Status :: 3 - Alpha
Classifier: License :: OSI Approved :: GNU General Public License v3 (GPLv3)
Classifier: License :: Other/Proprietary License
Classifier: Operating System :: POSIX :: Linux
Classifier: Programming Language :: Python :: 3
Classifier: Programming Language :: Python :: 3.9
Classifier: Programming Language :: Python :: 3.10
Classifier: Programming Language :: Python :: 3.11
Classifier: Programming Language :: Python :: 3.12
Requires-Dist: httptools (>=0.6.1)
Requires-Dist: peewee (>=3.17.6,<4.0.0)
Requires-Dist: peewee-migrate (>=1.12.2,<2.0.0)
Requires-Dist: python-dotenv (>=1.0.1)
Requires-Dist: requests (>=2.31.0)
Requires-Dist: upnpclient (>=1.0.3)
Requires-Dist: urllib3 (>=2.1.0)
Requires-Dist: whatismyip (>=2022.7.10)
Project-URL: Repository, https://github.com/Web3-Pi/web3-reverse-proxy
